rest_dataclasses/__init__.py
rest_dataclasses/__version__.py
rest_dataclasses/serializers.py
rest_dataclasses/utils.py
django_rest_dataclasses-0.0.3.dist-info/LICENSE
django_rest_dataclasses-0.0.3.dist-info/METADATA
django_rest_dataclasses-0.0.3.dist-info/WHEEL
django_rest_dataclasses-0.0.3.dist-info/top_level.txt
django_rest_dataclasses-0.0.3.dist-info/RECORD
